Metadata-Version: 2.1
Name: georgecluu
Version: 0.0.0
Summary: A very basic calculator
Home-page: https://github.com/Georgepop/api_my_task
Author: George
Author-email: pavlovgeorgem@yandex.ru
License: MIT
Keywords: calculator
Platform: UNKNOWN
Classifier: Development Status :: 5 - Production/Stable
Classifier: Intended Audience :: Education
Classifier: Operating System :: Microsoft :: Windows :: Windows 10
Classifier: License :: OSI Approved :: MIT License
Classifier: Programming Language :: Python :: 3
Requires-Python: >=3.5
License-File: LICENSE.txt
